[
  {
    "children": [],
    "diji": "",
    "quHuaDaiMa": "451102",
    "quhao": "0774",
    "shengji": "",
    "xianji": "八步区"
  },
  {
    "children": [],
    "diji": "",
    "quHuaDaiMa": "451103",
    "quhao": "0774",
    "shengji": "",
    "xianji": "平桂区"
  },
  {
    "children": [],
    "diji": "",
    "quHuaDaiMa": "451121",
    "quhao": "0774",
    "shengji": "",
    "xianji": "昭平县"
  },
  {
    "children": [],
    "diji": "",
    "quHuaDaiMa": "451122",
    "quhao": "0774",
    "shengji": "",
    "xianji": "钟山县"
  },
  {
    "children": [],
    "diji": "",
    "quHuaDaiMa": "451123",
    "quhao": "0774",
    "shengji": "",
    "xianji": "富川瑶族自治县"
  }
]