[
  {
    "children": [],
    "diji": "",
    "quHuaDaiMa": "320411",
    "quhao": "0519",
    "shengji": "",
    "xianji": "新北区"
  },
  {
    "children": [],
    "diji": "",
    "quHuaDaiMa": "320402",
    "quhao": "0519",
    "shengji": "",
    "xianji": "天宁区"
  },
  {
    "children": [],
    "diji": "",
    "quHuaDaiMa": "320404",
    "quhao": "0519",
    "shengji": "",
    "xianji": "钟楼区"
  },
  {
    "children": [],
    "diji": "",
    "quHuaDaiMa": "320412",
    "quhao": "0519",
    "shengji": "",
    "xianji": "武进区"
  },
  {
    "children": [],
    "diji": "",
    "quHuaDaiMa": "320413",
    "quhao": "0519",
    "shengji": "",
    "xianji": "金坛区"
  },
  {
    "children": [],
    "diji": "",
    "quHuaDaiMa": "320481",
    "quhao": "0519",
    "shengji": "",
    "xianji": "溧阳市"
  }
]