[
  {
    "children": [],
    "diji": "贵阳市",
    "quHuaDaiMa": "520100",
    "quhao": "0851",
    "shengji": "",
    "xianji": ""
  },
  {
    "children": [],
    "diji": "六盘水市",
    "quHuaDaiMa": "520200",
    "quhao": "0858",
    "shengji": "",
    "xianji": ""
  },
  {
    "children": [],
    "diji": "遵义市",
    "quHuaDaiMa": "520300",
    "quhao": "0851",
    "shengji": "",
    "xianji": ""
  },
  {
    "children": [],
    "diji": "安顺市",
    "quHuaDaiMa": "520400",
    "quhao": "0851",
    "shengji": "",
    "xianji": ""
  },
  {
    "children": [],
    "diji": "毕节市",
    "quHuaDaiMa": "520500",
    "quhao": "0857",
    "shengji": "",
    "xianji": ""
  },
  {
    "children": [],
    "diji": "铜仁市",
    "quHuaDaiMa": "520600",
    "quhao": "0856",
    "shengji": "",
    "xianji": ""
  },
  {
    "children": [],
    "diji": "黔西南布依族苗族自治州",
    "quHuaDaiMa": "522300",
    "quhao": "0859",
    "shengji": "",
    "xianji": ""
  },
  {
    "children": [],
    "diji": "黔东南苗族侗族自治州",
    "quHuaDaiMa": "522600",
    "quhao": "0855",
    "shengji": "",
    "xianji": ""
  },
  {
    "children": [],
    "diji": "黔南布依族苗族自治州",
    "quHuaDaiMa": "522700",
    "quhao": "0854",
    "shengji": "",
    "xianji": ""
  }
]